{
  "id": "4476867",
  "name": "demo",
  "font_family": "iconfont",
  "css_prefix_text": "icon-",
  "description": "",
  "glyphs": [
    {
      "icon_id": "7852021",
      "name": "list",
      "font_class": "list",
      "unicode": "e620",
      "unicode_decimal": 58912
    },
    {
      "icon_id": "21096548",
      "name": "angle-up",
      "font_class": "angle-up",
      "unicode": "eca3",
      "unicode_decimal": 60579
    },
    {
      "icon_id": "4937000",
      "name": "github-fill",
      "font_class": "github-fill",
      "unicode": "e885",
      "unicode_decimal": 59525
    },
    {
      "icon_id": "6568050",
      "name": "写博客",
      "font_class": "xieboke",
      "unicode": "e624",
      "unicode_decimal": 58916
    },
    {
      "icon_id": "34453204",
      "name": "email-fill",
      "font_class": "email-fill",
      "unicode": "e856",
      "unicode_decimal": 59478
    },
    {
      "icon_id": "27365294",
      "name": "steam",
      "font_class": "steam",
      "unicode": "ec22",
      "unicode_decimal": 60450
    }
  ]
}
